Workbook

Sheet Hoja1
B1: kw | C1: $km | D1: valor tota | E1: precio | F1: alumbrado | G1: precio final | H1: proporcion 20 dias
B2: 130 | C2: 814.6887 | D2: =+C2*B2 -> 105909.53 | E2: =+D2+D3 -> 331147 | F2: 9696 | G2: =+F2+E2 -> 340843
B3: 235 | C3: 958.4573 | D3: =+C3*B3 -> 225237.47
B5: =+B2/2 -> 65 | C5: 814.6887 | D5: =+C5*B5 -> 52954.766 | E5: =+D5+D6 -> 184263.42 | F5: 9696 | G5: =+F5+E5 -> 193959.42 | H5: =+G5*0.7 -> 135771.59
B6: =+C13 -> 137 | C6: 958.4573 | D6: =+C6*B6 -> 131308.65
B8: 163 | C8: 65 | D8: 814.6887 | E8: =+D8*C8 -> 52954.766 | F8: =+E8+E9 -> 146883.58 | G8: 9696 | H8: =+G8+F8 -> 156579.58
C9: =B8-C8 -> 98 | D9: 958.4573 | E9: =+D9*C9 -> 93928.815
B12: =365-163 -> 202 | C12: 65
C13: =+B12-C12 -> 137
B15: 555 | C15: 130 | D15: 814.6887 | E15: =+D15*C15 -> 105909.53 | F15: =+E15+E16 -> 513253.88 | G15: =+G8 -> 9696 | H15: =+G15+F15 -> 522949.88
C16: =+B15-C15 -> 425 | D16: 958.4573 | E16: =+D16*C16 -> 407344.35 | J16: =+H15-H18 -> 146883.58
B18: 392 | C18: 65 | D18: 814.6887 | E18: =+D18*C18 -> 52954.766 | F18: =+E18+E19 -> 366370.3 | G18: =+G15 -> 9696 | H18: =+G18+F18 -> 376066.3
C19: =+B18-C18 -> 327 | D19: 958.4573 | E19: =+D19*C19 -> 313415.54

Sheet Servicios
A1: mes | B1: kw total | C1: kw -cesar | D1: kw | E1: $km | F1: valor total | G1: precio | H1: alumbrado | I1: precio final
A2: Febrero | B2: 365 | C2: =+B2-163 -> 202 | D2: 65 | E2: 814.6887 | F2: =+E2*D2 -> 52954.766 | G2: =+F2+F3 -> 184263.42 | H2: 9696 | I2: =+H2+G2 -> 193959.42 | J2: 340843
D3: =+C2-D2 -> 137 | E3: 958.4573 | F3: =+E3*D3 -> 131308.65 | J3: =+J2-I2 -> 146883.58
A4: marzo | B4: 273 | C4: =+B4-163 -> 110 | D4: =130/2 -> 65 | E4: 815.5131 | F4: =+E4*D4 -> 53008.351 | G4: =+F4+F5 -> 96182.576 | H4: 9696 | I4: =+H4+G4 -> 105878.58 | J4: 253290
D5: =+C4-D4 -> 45 | E5: 959.4272 | F5: =+E5*D5 -> 43174.224 | J5: =+J4-I4 -> 147411.42
A6: abril | B6: 461 | C6: =+B6-163 -> 298 | D6: 65 | E6: 799.3542 | F6: =+E6*D6 -> 51958.023 | G6: =+F6+F7 -> 271075.11 | H6: 9696 | I6: =+H6+G6 -> 280771.11 | J6: 416428
D7: =+C6-D6 -> 233 | E7: 940.4167 | F7: =+E7*D7 -> 219117.09 | J7: =+J6-I6 -> 135656.89
A8: mayo
A10: junio
A12: julio | B12: 366 | C12: =+B12-163 -> 203 | D12: 65 | E12: 849.2424 | F12: =+E12*D12 -> 55200.756 | G12: =+F12+F13 -> 193077.76 | H12: 9696 | I12: =+H12+G12 -> 202773.76 | J12: 355887
D13: =+C12-D12 -> 138 | E13: 999.1087 | F13: =+E13*D13 -> 137877 | J13: =+J12-I12 -> 153113.24
A14: agosto | B14: 426 | C14: =+B14-163 -> 263 | D14: 65 | E14: 865.5551 | F14: =+E14*D14 -> 56261.082 | G14: =+F14+F15 -> 257884.5 | H14: 9696 | I14: =+H14+G14 -> 267580.5 | J14: 423861
D15: =+C14-D14 -> 198 | E15: 1018.3001 | F15: =+E15*D15 -> 201623.42 | J15: =+J14-I14 -> 156280.5
A16: septiembre | B16: 426 | C16: =+B16-163 -> 263 | D16: 65 | E16: 865.5551 | F16: =+E16*D16 -> 56261.082 | G16: =+F16+F17 -> 257884.5 | H16: 9696 | I16: =+H16+G16 -> 267580.5 | J16: 423861
D17: =+C16-D16 -> 198 | E17: 1018.3001 | F17: =+E17*D17 -> 201623.42 | J17: =+J16-I16 -> 156280.5

Sheet Costo Fijos
A1: Gastos fijos
A2: arriendo | B2: 900000
A3: credito | B3: 460000
A4: empleado | B4: 1300000
B5: =+SUM(B2:B4) -> 2660000

Sheet Gastos
A1: enero | B1: febrero | C1: marzo | D1: abril | E1: mayo | F1: junio | G1: julio | H1: agosto | I1: septiembre | J1: octubre | K1: noviembre | L1: diciembre
A2: =65000+271300+372000+312200+581400+32600+10000+65600 -> 1710100 | B2: 131000 | C2: 260900 | D2: =16400+24600 -> 41000 | E2: 108000 | F2: 94500 | G2: 397000 | H2: 312000 | I2: 285100 | J2: 50000 | K2: 548100 | L2: 607000
A3: 450000 | B3: =189500+32800 -> 222300 | C3: 52000 | D3: =400000+54000+8200 -> 462200 | E3: 300700 | F3: 301600 | G3: 863300 | H3: 348800 | I3: 72600 | J3: 202900 | K3: 311700 | L3: 270500
A4: =282800+49200+15000+78200+49200+72600+19000+21000 -> 587000 | B4: 479200 | C4: 121700 | D4: 317600 | E4: 865000 | F4: 187200 | G4: 219000 | H4: 255400 | I4: 436500 | J4: 266000 | K4: 207000 | L4: 74100
A5: 10000 | B5: 68100 | C5: 222800 | D5: 399500 | E5: 209600 | F5: 54700 | G5: 59900 | H5: 234500 | I5: 150600 | J5: 137000 | K5: 228700 | L5: 480900
A6: 41000 | B6: 53700 | C6: 115500 | D6: 343000 | E6: 24600 | F6: 393100 | G6: 116900 | H6: 207900 | I6: 261800 | J6: 133500 | K6: 392500 | L6: 202800
A7: =98500+96000 -> 194500 | B7: 75300 | C7: 185000 | D7: 144400 | E7: 251100 | F7: 104600 | G7: 427600 | H7: 93500 | I7: 132100 | J7: 156600 | K7: 306200 | L7: 334300
A8: =108200+30000 -> 138200 | B8: 89600 | C8: 104500 | D8: 328500 | E8: 337800 | F8: 308000 | G8: 200000 | H8: 211200 | I8: 232300 | J8: 204600 | K8: 68000 | L8: 82000
A9: =26000+191000+121200+16200 -> 354400 | B9: 78000 | C9: 78500 | D9: 584400 | E9: 478400 | F9: 92800 | G9: 49200 | H9: 222100 | I9: 127000 | J9: 319600 | K9: 276900 | L9: 471800
A10: =10500+4000+14500+14500 -> 43500 | B10: 242600 | C10: 198000 | D10: 45600 | E10: 79000 | F10: 259100 | G10: 118100 | H10: 221500 | I10: 74600 | J10: 253300 | K10: 190100 | L10: 182800
A11: =4000+4000+4000 -> 12000 | B11: 141800 | C11: 368900 | D11: 174400 | E11: 256500 | F11: 774400 | G11: 93500 | H11: 24600 | I11: 24900 | J11: 206800 | K11: 247600 | L11: 27100
A12: 130600 | B12: 40500 | C12: 24000 | D12: 236000 | E12: 63000 | F12: 186400 | G12: 177000 | H12: 329500 | I12: 148600 | J12: 73000 | K12: 715400 | L12: 38800
B13: 296700 | C13: 395200 | D13: 218200 | E13: 108000 | F13: 674500 | G13: 876500 | H13: 16400 | I13: 386800 | J13: 300800 | K13: 483800 | L13: 500900
B14: 77000 | C14: 181500 | D14: 57400 | E14: =1254000-650000 -> 604000 | F14: 191800 | G14: 206500 | H14: 306400 | I14: 154600 | J14: 152800 | K14: 427400 | L14: 434600
B15: 152100 | C15: 123800 | D15: 437200 | E15: 36500 | F15: 24600 | G15: 225000 | H15: 331800 | I15: 120800 | J15: 508900 | K15: 110300 | L15: 63800
B16: 101000 | C16: 916400 | D16: 122000 | E16: 185500 | F16: 239900 | G16: 135800 | H16: 218000 | I16: 240000 | J16: 16400 | K16: 156800 | L16: 563100
B17: 922500 | C17: 224600 | D17: 45200 | E17: 59700 | F17: 987000 | G17: 197600 | H17: 106600 | I17: 202400 | J17: 128900 | K17: 66400 | L17: 13000
B18: 25000 | C18: 303200 | D18: 102100 | E18: 59500 | F18: 180600 | G18: 176600 | H18: 222600 | I18: 62600 | J18: 254600 | K18: 211800 | L18: 840000
B19: 414000 | C19: 178000 | D19: 480000 | E19: 156400 | F19: 93100 | G19: 582100 | H19: 333800 | I19: 354400 | J19: 125100 | K19: 284200 | L19: 389000
B20: 73800 | C20: 336700 | D20: 181100 | E20: 150000 | F20: 182600 | G20: 225000 | H20: 102600 | I20: 66400 | J20: 118000 | K20: 243900 | L20: 130000
B21: 144200 | C21: 6000 | D21: 82100 | E21: 106200 | F21: 234000 | G21: 74900 | H21: 41000 | I21: 290800 | J21: 212800 | K21: 230000 | L21: 280000
B22: 271000 | C22: 84500 | D22: 322300 | E22: 268800 | F22: 174200 | G22: 120300 | H22: 178500 | I22: 121000 | J22: 58000 | K22: 101000
B23: =224000+100000 -> 324000 | D23: 116400 | E23: 360700 | F23: 55400 | G23: 45000 | H23: 270100 | I23: 939600 | J23: 187500 | K23: 73500
B24: 122500 | D24: 24000 | E24: =769600-650000 -> 119600 | G24: 851000 | H24: 512000 | J24: 62400 | K24: 362000
B25: 134300 | E25: 69500 | G25: 78800 | J25: 309500
G26: 78200 | J26: 197600
J27: 163800
A28: =+SUM(A2:A26) -> 3671300 | B28: =+SUM(B2:B26) -> 4680200 | C28: =+SUM(C2:C26) -> 4481700 | D28: =+SUM(D2:D26) -> 5264600 | E28: =+SUM(E2:E26) -> 5258100 | F28: =+SUM(F2:F26) -> 5794100 | G28: =+SUM(G2:G26) -> 6594800 | H28: =+SUM(H2:H26) -> 5100800 | I28: =+SUM(I2:I26) -> 4885500 | J28: =+SUM(J2:J27) -> 4800400 | K28: =+SUM(K2:K26) -> 6243300 | L28: =+SUM(L2:L26) -> 5986500
A29: =+'Costo Fijos'!B5 -> 2660000 | B29: =+'Costo Fijos'!B5 -> 2660000 | C29: =+'Costo Fijos'!B5 -> 2660000 | D29: =+'Costo Fijos'!B5 -> 2660000 | E29: =+'Costo Fijos'!B5 -> 2660000 | F29: =+'Costo Fijos'!B5 -> 2660000 | G29: =+'Costo Fijos'!B5 -> 2660000 | H29: =+'Costo Fijos'!B5 -> 2660000 | I29: =+'Costo Fijos'!B5 -> 2660000 | J29: =+'Costo Fijos'!B5 -> 2660000 | K29: =+'Costo Fijos'!B5+650000 -> 3310000 | L29: =+'Costo Fijos'!B5 -> 2660000
F30: -900000 | G30: -1300000
A31: =+A28+A29+A30 -> 6331300 | B31: =+B28+B29+B30 -> 7340200 | C31: =+C28+C29+C30 -> 7141700 | D31: =+D28+D29+D30 -> 7924600 | E31: =+E28+E29+E30 -> 7918100 | F31: =+F28+F29+F30 -> 7554100 | G31: =+G28+G29+G30 -> 7954800 | H31: =+H28+H29+H30 -> 7760800 | ... L31: =+L28+L29+L30 -> 8646500

Sheet Ingreso
A1: enero | B1: febrero | C1: marzo | D1: abril | E1: mayo | F1: junio | G1: julio | H1: agosto | I1: septiembre | J1: octubre | K1: noviembre | L1: diciembre
A2: 186000 | B2: 234200 | C2: 353900 | D2: 551500 | E2: 338800 | F2: 368700 | G2: 362200 | H2: 331400 | I2: 318900 | J2: 178400 | K2: 869700 | L2: 129700
A3: 906000 | B3: 436900 | C3: 593200 | D3: 222250 | E3: 246000 | F3: 389200 | G3: 363600 | H3: 457400 | I3: 881700 | J3: 497700 | K3: 568000 | L3: 566700
A4: 519000 | B4: 423800 | C4: 275500 | D4: 356350 | E4: 360000 | F4: 564300 | G4: 322800 | H4: 256200 | I4: 359200 | J4: 520100 | K4: 434500 | L4: 606800
A5: 319500 | B5: 256700 | C5: 374400 | D5: 244950 | E5: 659350 | F5: 386500 | G5: 661900 | H5: 202400 | I5: 376500 | J5: 270000 | K5: 649800 | L5: 415900
A6: 322000 | B6: 336100 | C6: 434500 | D6: 241000 | E6: 574650 | F6: 263800 | G6: 312300 | H6: 774200 | I6: 300500 | J6: 282800 | K6: 411300 | L6: 494500
A7: 447200 | B7: 336700 | C7: 370200 | D7: 529500 | E7: 260600 | F7: 510300 | G7: 869200 | H7: 293800 | I7: 253100 | J7: 212300 | K7: 479900 | L7: 257800
A8: 345800 | B8: 162000 | C8: 247900 | D8: 407900 | E8: 245600 | F8: 351100 | G8: 174600 | H8: 302300 | I8: 186400 | J8: 941100 | K8: 641800 | L8: 184800
A9: 545000 | B9: 245500 | C9: 752600 | D9: 507400 | E9: 306550 | F9: 264800 | G9: 357600 | H9: 218000 | I9: 118600 | J9: 233800 | K9: 591900 | L9: 98000
A10: 153600 | B10: 340700 | C10: 339600 | D10: 305300 | E10: 317100 | F10: 259300 | G10: 265000 | H10: 453900 | I10: 642100 | J10: 432000 | K10: 305900 | L10: 304000
A11: 443900 | B11: 226400 | C11: 290900 | D11: 288200 | E11: 286500 | F11: 400300 | G11: 480900 | H11: 142900 | I11: 202600 | J11: 208000 | K11: 619700 | L11: 344400
A12: 359500 | B12: 223200 | C12: 151300 | D12: 334950 | E12: 328300 | F12: 438100 | G12: 314500 | H12: 383200 | I12: 383700 | J12: 436100 | K12: 298700 | L12: 398800
B13: 173100 | C13: 131100 | D13: 413500 | E13: 148900 | F13: 172100 | G13: 87400 | H13: 393200 | I13: 293900 | J13: 284800 | K13: 734000 | L13: 297000
B14: 204200 | C14: 358300 | D14: 392800 | E14: 500900 | F14: 362600 | G14: 147500 | H14: 402200 | I14: 433200 | J14: 251500 | K14: 117300 | L14: 462700
B15: 221800 | C15: 416700 | D15: 95000 | E15: 321700 | F15: 240600 | G15: 706400 | H15: 347000 | I15: 354000 | J15: 488300 | K15: 374500 | L15: 869100
B16: 404800 | C16: 463900 | D16: 256000 | E16: 221400 | F16: 292100 | G16: 346400 | H16: 521400 | I16: 468200 | J16: 278200 | K16: 350400 | L16: 464200
B17: 170300 | C17: 392200 | D17: 250100 | E17: 535250 | F17: 368800 | G17: 251600 | H17: 440900 | I17: 263000 | J17: 365500 | K17: 373500 | L17: 511700
B18: 276500 | C18: 187000 | D18: 255400 | E18: 219000 | F18: 294000 | G18: 448800 | H18: 226800 | I18: 223500 | J18: 514600 | K18: 411700 | L18: 557700
B19: 294500 | C19: 203300 | D19: 223200 | E19: 214550 | F19: 257900 | G19: 265800 | H19: 482300 | I19: 283700 | J19: 248800 | K19: 721400
B20: 302600 | C20: 333000 | D20: 240000 | E20: 144100 | F20: 336800 | G20: 185300 | H20: 511200 | I20: 630000 | J20: 385400 | K20: 465200
B21: 291100 | C21: 320700 | D21: 283100 | E21: 484300 | F21: 329100 | G21: 243500 | H21: 325200 | I21: 341300 | J21: 554600 | K21: 696000
B22: 332600 | C22: 284000 | D22: 348200 | E22: 493600 | F22: 296700 | G22: 512400 | H22: 223000 | I22: 238700 | J22: 204600 | K22: 275900
B23: 556600 | C23: 373000 | D23: 341000 | E23: 281000 | F23: 174200 | G23: 430000 | H23: 305200 | I23: 367200 | J23: 168400 | K23: 656400
B24: 281800 | D24: 732000 | E24: 102600 | F24: 315000 | G24: 241300 | H24: 548200 | I24: 246000 | J24: 683600 | K24: 745500
B25: 228400 | D25: 391600 | E25: 391000 | G25: 128400 | H25: 227300 | I25: 128300 | J25: 558400
B26: 331200 | D26: 224000 | E26: 369500 | G26: 547700 | H26: 448000 | I26: 281800 | J26: 158700
D27: 334750 | G27: 156800 | J27: 164000
G28: 339300
A29: =+SUM(A2:A28) -> 4547500 | B29: =+SUM(B2:B28) -> 7291700 | C29: =+SUM(C2:C28) -> 7647200 | D29: =+SUM(D2:D28) -> 8769950 | E29: =+SUM(E2:E28) -> 8351250 | F29: =+SUM(F2:F28) -> 7636300 | G29: =+SUM(G2:G28) -> 9523200 | H29: =+SUM(H2:H28) -> 9217600 | ... O29: =+SUM(O2:O28) -> 0

Sheet Balance
A1: mes | B1: enero | C1: febrero | D1: marzo | E1: abril | F1: mayo | G1: junio | H1: julio | I1: agosto | J1: septiembre | K1: octubre | L1: noviembre | M1: diciembre
A2: egreso | B2: =+Gastos!A31 -> 6331300 | C2: =+Gastos!B31 -> 7340200 | D2: =+Gastos!C31 -> 7141700 | E2: =+Gastos!D31 -> 7924600 | F2: =+Gastos!E31 -> 7918100 | G2: =+Gastos!F31 -> 7554100 | H2: =+Gastos!G31 -> 7954800 | I2: =+Gastos!H31 -> 7760800 | ... M2: =+Gastos!L31 -> 8646500
A3: ingreso | B3: =+Ingreso!A29 -> 4547500 | C3: =+Ingreso!B29 -> 7291700 | D3: =+Ingreso!C29 -> 7647200 | E3: =+Ingreso!D29 -> 8769950 | F3: =+Ingreso!E29 -> 8351250 | G3: =+Ingreso!F29 -> 7636300 | H3: =+Ingreso!G29 -> 9523200 | I3: =+Ingreso!H29 -> 9217600 | ... M3: =+Ingreso!L29 -> 6963800
A4: balance | B4: =+B3-B2 -> -1783800 | C4: =+C3-C2 -> -48500 | D4: =+D3-D2 -> 505500 | E4: =+E3-E2 -> 845350 | F4: =+F3-F2 -> 433150 | G4: =+G3-G2 -> 82200 | H4: =+H3-H2 -> 1568400 | I4: =+I3-I2 -> 1456800 | ... M4: =+M3-M2 -> -1682700
A5: %utilidad | B5: =(B3/B2)-1 -> -0.28174309 | C5: =(C3/C2)-1 -> -0.0066074494 | D5: =(D3/D2)-1 -> 0.070781467 | E5: =(E3/E2)-1 -> 0.10667415 | F5: =(F3/F2)-1 -> 0.05470378 | G5: =(G3/G2)-1 -> 0.010881508 | H5: =(H3/H2)-1 -> 0.19716398 | I5: =(I3/I2)-1 -> 0.18771261 | ... M5: =(M3/M2)-1 -> -0.19461054
K7: =+L2-K2 -> 2092900 | L7: =+K2*100/L2 -> 78.092387 | M7: =100-L7 -> 21.907613
B8: =+K2/26 -> 286938.46 | K8: =+L3-K3 -> 2271300 | L8: =+K3*100/L3 -> 80.74027 | M8: =100-L8 -> 19.25973
B9: =+L2/26 -> 367434.62 | K9: =+K8-K7 -> 178400
B10: =10000000/26 -> 384615.38

Sheet Costo de produccion
A1: empanada de carne | I1: empanada de pollo | Q1: queso
A2: insumo | B2: precio | C2: precio/kg insumo | D2: gr de uso | E2: kg de uso | F2: precio del insumo usado | G2: precio*emp | I2: insumo | J2: precio | K2: precio/kg insumo | L2: gr de uso | M2: kg de uso | N2: precio del insumo usado | O2: precio*emp | Q2: insumo | R2: precio | S2: precio/kg insumo | T2: gr de uso | U2: kg de uso | V2: precio del insumo usado | W2: precio*emp
A3: tomate | B3: 13000 | C3: =(B3/15) -> 866.66667 | D3: 323 | E3: =+D3/1000 -> 0.323 | F3: =+E3*C3 -> 279.93333 | G3: =+F3/300 -> 0.93311111 | I3: tomate | J3: 13000 | K3: =(J3/15) -> 866.66667 | L3: 323 | M3: =+L3/1000 -> 0.323 | N3: =+M3*K3 -> 279.93333 | O3: =+N3/300 -> 0.93311111 | Q3: mozarela | R3: 75000 | S3: =+R3/2.5 -> 30000 | T3: 2500 | U3: =+T3/1000 -> 2.5 | V3: =+S3*U3 -> 75000 | W3: =+V3/300 -> 250
A4: pimenton | B4: 7000 | C4: =B4/4 -> 1750 | D4: 215 | E4: =+D4/1000 -> 0.215 | F4: =+E4*C4 -> 376.25 | G4: =+F4/300 -> 1.2541667 | I4: pimenton | J4: 7000 | K4: =J4/4 -> 1750 | L4: 215 | M4: =+L4/1000 -> 0.215 | N4: =+M4*K4 -> 376.25 | O4: =+N4/300 -> 1.2541667 | Q4: cuaja | R4: 48000 | S4: =+R4/5 -> 9600 | T4: 5000 | U4: =+T4/1000 -> 5 | V4: =+S4*U4 -> 48000 | W4: =+V4/300 -> 160
A5: cebolla | B5: 60000 | C5: =B5/30 -> 2000 | D5: 176 | E5: =+D5/1000 -> 0.176 | F5: =+E5*C5 -> 352 | G5: =+F5/300 -> 1.1733333 | I5: cebolla | J5: 60000 | K5: =J5/30 -> 2000 | L5: 176 | M5: =+L5/1000 -> 0.176 | N5: =+M5*K5 -> 352 | O5: =+N5/300 -> 1.1733333 | Q5: masa | R5: 8200 | S5: =+R5/6 -> 1366.6667 | T5: =6000*3 -> 18000 | U5: =+T5/1000 -> 18 | V5: =+U5*S5 -> 24600 | W5: =+V5/300 -> 82
A6: sal | B6: 1500 | C6: =+B6/1 -> 1500 | D6: 82 | E6: =+D6/1000 -> 0.082 | F6: =+E6*C6 -> 123 | G6: =+F6/300 -> 0.41 | I6: sal | J6: 1500 | K6: =+J6/1 -> 1500 | L6: 82 | M6: =+L6/1000 -> 0.082 | N6: =+M6*K6 -> 123 | O6: =+N6/300 -> 0.41 | Q6: sal | R6: 1500 | S6: =+R6/1 -> 1500 | T6: =57*3 -> 171 | U6: =+T6/1000 -> 0.171 | V6: =+U6*S6 -> 256.5 | W6: =+V6/300 -> 0.855
A7: comino | B7: 23000 | C7: =+B7/1 -> 23000 | D7: 10 | E7: =+D7/1000 -> 0.01 | F7: =+E7*C7 -> 230 | G7: =+F7/300 -> 0.76666667 | I7: comino | J7: 23000 | K7: =+J7/1 -> 23000 | L7: 10 | M7: =+L7/1000 -> 0.01 | N7: =+M7*K7 -> 230 | O7: =+N7/300 -> 0.76666667 | P7: =+O7+O6+O5+O4+O3 -> 4.5372778 | Q7: fecula | R7: 6500 | S7: =+R7/1 -> 6500 | T7: =208*3 -> 624 | U7: =+T7/1000 -> 0.624 | V7: =+U7*S7 -> 4056 | W7: =+V7/300 -> 13.52
A8: papa | B8: 70000 | C8: =+B8/50 -> 1400 | D8: 7000 | E8: =+D8/1000 -> 7 | F8: =+C8*E8 -> 9800 | G8: =+F8/300 -> 32.666667 | I8: papa | J8: 70000 | K8: =+J8/50 -> 1400 | L8: 5000 | M8: =+L8/1000 -> 5 | N8: =+K8*M8 -> 7000 | O8: =+N8/300 -> 23.333333 | Q8: almidon | R8: 9000 | S8: =+R8/1 -> 9000 | T8: =107*3 -> 321 | U8: =+T8/1000 -> 0.321 | V8: =+U8*S8 -> 2889 | W8: =+V8/300 -> 9.63
A9: carne | B9: 20000 | C9: =+B9/1 -> 20000 | D9: 3500 | E9: =+D9/1000 -> 3.5 | F9: =+C9*E9 -> 70000 | G9: =+F9/300 -> 233.33333 | I9: pollo | J9: 15000 | K9: =+J9/1 -> 15000 | L9: 5000 | M9: =+L9/1000 -> 5 | N9: =+K9*M9 -> 75000 | O9: =+N9/300 -> 250 | Q9: harina maiz | R9: 4500 | S9: =+R9/1 -> 4500 | T9: =82*3 -> 246 | U9: =+T9/1000 -> 0.246 | V9: =+U9*S9 -> 1107 | W9: =+V9/300 -> 3.69
A10: masa | B10: 8200 | C10: =+B10/6 -> 1366.6667 | D10: =6000*3 -> 18000 | E10: =+D10/1000 -> 18 | F10: =+E10*C10 -> 24600 | G10: =+F10/300 -> 82 | I10: masa | J10: 8200 | K10: =+J10/6 -> 1366.6667 | L10: =6000*3 -> 18000 | M10: =+L10/1000 -> 18 | N10: =+M10*K10 -> 24600 | O10: =+N10/300 -> 82 | Q10: luz | R10: 255000 | V10: =+R10/(300*6*4) -> 35.416667 | W10: =+R10/(300*6*4) -> 35.416667
A11: sal | B11: 1500 | C11: =+B11/1 -> 1500 | D11: =57*3 -> 171 | E11: =+D11/1000 -> 0.171 | F11: =+E11*C11 -> 256.5 | G11: =+F11/300 -> 0.855 | I11: sal | J11: 1500 | K11: =+J11/1 -> 1500 | L11: =57*3 -> 171 | M11: =+L11/1000 -> 0.171 | N11: =+M11*K11 -> 256.5 | O11: =+N11/300 -> 0.855 | Q11: agua | R11: 48000 | V11: =+R11/(300*6*4) -> 6.6666667 | W11: =+R11/(300*6*4) -> 6.6666667
A12: fecula | B12: 6500 | C12: =+B12/1 -> 6500 | D12: =208*3 -> 624 | E12: =+D12/1000 -> 0.624 | F12: =+E12*C12 -> 4056 | G12: =+F12/300 -> 13.52 | I12: fecula | J12: 6500 | K12: =+J12/1 -> 6500 | L12: =208*3 -> 624 | M12: =+L12/1000 -> 0.624 | N12: =+M12*K12 -> 4056 | O12: =+N12/300 -> 13.52 | Q12: gas | R12: 181000 | V12: =+R12/(300*6*4) -> 25.138889 | W12: =+R12/(300*6*4) -> 25.138889
A13: almidon | B13: 9000 | C13: =+B13/1 -> 9000 | D13: =107*3 -> 321 | E13: =+D13/1000 -> 0.321 | F13: =+E13*C13 -> 2889 | G13: =+F13/300 -> 9.63 | I13: almidon | J13: 9000 | K13: =+J13/1 -> 9000 | L13: =107*3 -> 321 | M13: =+L13/1000 -> 0.321 | N13: =+M13*K13 -> 2889 | O13: =+N13/300 -> 9.63 | Q13: aceite | R13: 115000 | V13: =+R13/(300*6*4) -> 15.972222 | W13: =+R13/(300*6*4) -> 15.972222
A14: harina maiz | B14: 4500 | C14: =+B14/1 -> 4500 | D14: =82*3 -> 246 | E14: =+D14/1000 -> 0.246 | F14: =+E14*C14 -> 1107 | G14: =+F14/300 -> 3.69 | I14: harina maiz | J14: 4500 | K14: =+J14/1 -> 4500 | L14: =82*3 -> 246 | M14: =+L14/1000 -> 0.246 | N14: =+M14*K14 -> 1107 | O14: =+N14/300 -> 3.69 | P14: =+SUM(O10:O14) -> 109.695 | Q14: empleado | R14: =+B19 -> 1423500 | S14: =+R14*2.5 -> 3558750 | T14: =+S14/30 -> 118625 | U14: =+T14/8 -> 14828.125 | V14: =+U14/180 -> 82.378472 | W14: =+V14 -> 82.378472
A15: luz | B15: 255000 | F15: =+B15/(300*6*4) -> 35.416667 | G15: =+B15/(300*6*4) -> 35.416667 | I15: luz | J15: 255000 | N15: =+J15/(300*6*4) -> 35.416667 | O15: =+J15/(300*6*4) -> 35.416667 | V15: CPr | W15: =SUM(W3:W14) -> 685.26792
A16: agua | B16: 48000 | F16: =+B16/(300*6*4) -> 6.6666667 | G16: =+B16/(300*6*4) -> 6.6666667 | I16: agua | J16: 48000 | N16: =+J16/(300*6*4) -> 6.6666667 | O16: =+J16/(300*6*4) -> 6.6666667 | V16: PV | W16: =+W15/(1-0.45) -> 1245.9417
A17: gas | B17: 181000 | F17: =+B17/(300*6*4) -> 25.138889 | G17: =+B17/(300*6*4) -> 25.138889 | I17: gas | J17: 181000 | N17: =+J17/(300*6*4) -> 25.138889 | O17: =+J17/(300*6*4) -> 25.138889 | P17: =+SUM(O15:O17) -> 67.222222 | V17: Pe | W17: =+'Costo Fijos'!B5/(W16-W15) -> 4744.292
A18: aceite | B18: 115000 | F18: =+B18/(300*6*4) -> 15.972222 | G18: =+B18/(300*6*4) -> 15.972222 | I18: aceite | J18: 115000 | N18: =+J18/(300*6*4) -> 15.972222 | O18: =+J18/(300*6*4) -> 15.972222
A19: empleado | B19: 1423500 | C19: =+B19*2.5 -> 3558750 | D19: =+C19/30 -> 118625 | E19: =+D19/8 -> 14828.125 | F19: =+E19/180 -> 82.378472 | G19: =+F19 -> 82.378472 | I19: empleado | J19: =+B19 -> 1423500 | K19: =+J19*2.5 -> 3558750 | L19: =+K19/30 -> 118625 | M19: =+L19/8 -> 14828.125 | N19: =+M19/180 -> 82.378472 | O19: =+N19 -> 82.378472
F20: CPr | G20: =SUM(G3:G19) -> 545.80519 | N20: CPr | O20: =SUM(O3:O19) -> 553.13853
F21: PV | G21: =+G20/(1-0.45) -> 992.37308 | N21: PV | O21: =+O20/(1-0.45) -> 1005.7064
F22: Pe | G22: =+'Costo Fijos'!B5/(G21-G20) -> 5956.5412 | N22: Pe | O22: =+'Costo Fijos'!B5/(O21-O20) -> 5877.5713
I23: 80
I24: 95 | J24: =900*0.095 -> 85.5
I25: 70 | J25: =24000/25 -> 960 | L25: 900000 | M25: =+L25/26 -> 34615.385 | N25: =+M25/300 -> 115.38462
I26: 85 | J26: =22000/25 -> 880
I27: 25

Sheet Costo de produccion (2)
A1: carne
A2: insumo | B2: precio | C2: precio/kg insumo | D2: gr de uso | E2: kg de uso | F2: precio del insumo usado | G2: precio*emp
A3: tomate | B3: 13000 | C3: =(B3/15) -> 866.66667 | D3: 323 | E3: =+D3/1000 -> 0.323 | F3: =+E3*C3 -> 279.93333 | G3: =+F3/300 -> 0.93311111
A4: pimenton | B4: 7000 | C4: =B4/4 -> 1750 | D4: 215 | E4: =+D4/1000 -> 0.215 | F4: =+E4*C4 -> 376.25 | G4: =+F4/300 -> 1.2541667
A5: cebolla | B5: 60000 | C5: =B5/30 -> 2000 | D5: 176 | E5: =+D5/1000 -> 0.176 | F5: =+E5*C5 -> 352 | G5: =+F5/300 -> 1.1733333
A6: sal | B6: 1500 | C6: =+B6/1 -> 1500 | D6: 82 | E6: =+D6/1000 -> 0.082 | F6: =+E6*C6 -> 123 | G6: =+F6/300 -> 0.41
A7: comino | B7: 23000 | C7: =+B7/1 -> 23000 | D7: 10 | E7: =+D7/1000 -> 0.01 | F7: =+E7*C7 -> 230 | G7: =+F7/300 -> 0.76666667
A8: papa | B8: 70000 | C8: =+B8/50 -> 1400 | D8: 7000 | E8: =+D8/1000 -> 7 | F8: =+C8*E8 -> 9800 | G8: =+F8/300 -> 32.666667
A9: carne | B9: 20000 | C9: =+B9/1 -> 20000 | D9: 3500 | E9: =+D9/1000 -> 3.5 | F9: =+C9*E9 -> 70000 | G9: =+F9/300 -> 233.33333
A10: masa | B10: 8000 | C10: =+B10/6 -> 1333.3333 | D10: =6000*3 -> 18000 | E10: =+D10/1000 -> 18 | F10: =+E10*C10 -> 24000 | G10: =+F10/219 -> 109.58904 | H10: 73 | I10: =+H10*3 -> 219
A11: sal | B11: 1500 | C11: =+B11/1 -> 1500 | D11: =57*3 -> 171 | E11: =+D11/1000 -> 0.171 | F11: =+E11*C11 -> 256.5 | G11: =+F11/300 -> 0.855
A12: fecula | B12: 6500 | C12: =+B12/1 -> 6500 | D12: =208*3 -> 624 | E12: =+D12/1000 -> 0.624 | F12: =+E12*C12 -> 4056 | G12: =+F12/300 -> 13.52
A13: almidon | B13: 9000 | C13: =+B13/1 -> 9000 | D13: =107*3 -> 321 | E13: =+D13/1000 -> 0.321 | F13: =+E13*C13 -> 2889 | G13: =+F13/300 -> 9.63
A14: harina maiz | B14: 4500 | C14: =+B14/1 -> 4500 | D14: =82*3 -> 246 | E14: =+D14/1000 -> 0.246 | F14: =+E14*C14 -> 1107 | G14: =+F14/300 -> 3.69
A15: luz | B15: 255000 | F15: =+B15/(300*6*4) -> 35.416667 | G15: =+B15/(300*6*4) -> 35.416667
A16: agua | B16: 48000 | F16: =+B16/(300*6*4) -> 6.6666667 | G16: =+B16/(300*6*4) -> 6.6666667
A17: gas | B17: 181000 | F17: =+B17/(300*6*4) -> 25.138889 | G17: =+B17/(300*6*4) -> 25.138889
A18: aceite | B18: 115000 | F18: =+B18/(300*6*4) -> 15.972222 | G18: =+B18/(300*6*4) -> 15.972222
A19: empleado | B19: 1423500 | C19: =+B19*2.5 -> 3558750 | D19: =+C19/30 -> 118625 | E19: =+D19/8 -> 14828.125 | F19: =+E19/180 -> 82.378472 | G19: =+F19 -> 82.378472
F20: CPr | G20: =SUM(G3:G19) -> 573.39424
F21: PV | G21: =+G20/(1-0.45) -> 1042.535
F22: Pe | G22: =+'Costo Fijos'!B5/(G21-G20) -> 5669.9403
